dda/__init__.py
dda/api_client.py
dda/configuration.py
dda/rest.py
dda/api/__init__.py
dda/api/agent_api.py
dda/api/agent_list_api.py
dda/api/attachment_api.py
dda/api/database_list_api.py
dda/api/document_api.py
dda/api/document_list_api.py
dda/api/folder_api.py
dda/api/form_list_api.py
dda/api/view_design_api.py
dda/api/view_entry_list_api.py
dda/api/view_list_api.py
dda/models/__init__.py
dda/models/agent.py
dda/models/agent_job.py
dda/models/agent_list_response.py
dda/models/database.py
dda/models/database_list_response.py
dda/models/document.py
dda/models/document_list_entry.py
dda/models/document_list_response.py
dda/models/folder_operations.py
dda/models/form.py
dda/models/form_list_response.py
dda/models/link.py
dda/models/view.py
dda/models/view_column_design.py
dda/models/view_design_response.py
dda/models/view_entry.py
dda/models/view_entry_list_response.py
dda/models/view_list_response.py
test/__init__.py
test/test_agent.py
test/test_agent_api.py
test/test_agent_job.py
test/test_agent_list_api.py
test/test_agent_list_response.py
test/test_attachment_api.py
test/test_database.py
test/test_database_list_api.py
test/test_database_list_response.py
test/test_document.py
test/test_document_api.py
test/test_document_list_api.py
test/test_document_list_entry.py
test/test_document_list_response.py
test/test_folder_api.py
test/test_folder_operations.py
test/test_form.py
test/test_form_list_api.py
test/test_form_list_response.py
test/test_link.py
test/test_view.py
test/test_view_column_design.py
test/test_view_design_api.py
test/test_view_design_response.py
test/test_view_entry.py
test/test_view_entry_list_api.py
test/test_view_entry_list_response.py
test/test_view_list_api.py
test/test_view_list_response.py
dda-1.0.0.dist-info/LICENSE
dda-1.0.0.dist-info/METADATA
dda-1.0.0.dist-info/WHEEL
dda-1.0.0.dist-info/top_level.txt
dda-1.0.0.dist-info/RECORD
