Metadata-Version: 2.1
Name: dda
Version: 1.0.0
Summary: IBM Domino Data API
Home-page: 
Author-email: Radim Jaeger <rjaeger@sysnet.cz>
License: Apache License
Project-URL: Homepage, https://github.com/radimjager/dda
Keywords: Swagger,IBM Domino Data API
Classifier: Programming Language :: Python :: 3
Classifier: License :: OSI Approved :: Apache Software License
Classifier: Operating System :: OS Independent
Requires-Python: >=3.7
License-File: LICENSE
Requires-Dist: certifi (>=2017.4.17)
Requires-Dist: python-dateutil (>=2.1)
Requires-Dist: six (>=1.10)
Requires-Dist: urllib3 (>=1.23)
